twitch/__init__.py
twitch/twitch.py
twitchypy_irc-0.1.3.dist-info/LICENSE
twitchypy_irc-0.1.3.dist-info/METADATA
twitchypy_irc-0.1.3.dist-info/WHEEL
twitchypy_irc-0.1.3.dist-info/RECORD
