Metadata-Version: 2.1
Name: twitchypy_irc
Version: 0.1.3
Summary: Allows you to connect to Twitch IRC and send and receive messages.
Author: Elena Loonstra
Author-email: eloonstra@pm.me
Requires-Python: >=3.8,<4.0
Classifier: Programming Language :: Python :: 3
Classifier: Programming Language :: Python :: 3.8
Classifier: Programming Language :: Python :: 3.9
Classifier: Programming Language :: Python :: 3.10
Classifier: Programming Language :: Python :: 3.11
Classifier: Programming Language :: Python :: 3.12
Classifier: Programming Language :: Python :: 3.13
